engformat/__about__.py
engformat/__init__.py
engformat/geotech.py
engformat/plot.py
engformat/plot_acc_signal.py
engformat/plot_outputs.py
engformat/plot_tools.py
engformat/table.py
engformat-0.1.28.dist-info/LICENSE
engformat-0.1.28.dist-info/METADATA
engformat-0.1.28.dist-info/WHEEL
engformat-0.1.28.dist-info/top_level.txt
engformat-0.1.28.dist-info/RECORD
