Metadata-Version: 2.1
Name: engformat
Version: 0.1.28
Summary: Tools for displaying engineering calculations according to the Engineering Standard Format
Home-page: https://github.com/eng-tools/engformat
Author: Maxim Millen
Author-email: millen@fe.up.pt
License: MIT
Platform: UNKNOWN
Requires-Dist: numpy
Requires-Dist: bwplot (>=0.2.10)
Requires-Dist: sfsimodels
Requires-Dist: matplotlib
Requires-Dist: eqsig
